liastools/__init__.py
liastools-0.0.0.dist-info/LICENSE
liastools-0.0.0.dist-info/METADATA
liastools-0.0.0.dist-info/WHEEL
liastools-0.0.0.dist-info/top_level.txt
liastools-0.0.0.dist-info/RECORD
