Metadata-Version: 2.1
Name: liastools
Version: 0.0.0
Summary: Linux Astronomy Tools
Home-page: http://linux-astronomie.de
Author: Torsten Röhl
Author-email: devel@softure.de
Classifier: Programming Language :: Python :: 3
Classifier: License :: OSI Approved :: MIT License
Classifier: Operating System :: POSIX :: Linux
Requires-Python: >=3.7
License-File: LICENSE
